[{"date":"2024-03-08","total":4697,"delta":2,"version":"0.1.2018.08.10"},{"date":"2024-03-09","total":4699,"delta":2,"version":"0.1.2018.08.10"},{"date":"2024-03-10","total":4701,"delta":2,"version":"0.1.2018.08.10"},{"date":"2024-03-11","total":4703,"delta":2,"version":"0.1.2018.08.10"},{"date":"2024-03-12","total":4705,"delta":2,"version":"0.1.2018.08.10"},{"date":"2024-03-13","total":4707,"delta":2,"version":"0.1.2018.08.10"},{"date":"2024-03-14","total":4709,"delta":2,"version":"0.1.2018.08.10"},{"date":"2024-03-15","total":4713,"delta":4,"version":"0.1.2018.08.10"},{"date":"2024-03-16","total":4716,"delta":3,"version":"0.1.2018.08.10"},{"date":"2024-03-17","total":4718,"delta":2,"version":"0.1.2018.08.10"},{"date":"2024-03-18","total":4719,"delta":1,"version":"0.1.2018.08.10"},{"date":"2024-03-19","total":4721,"delta":2,"version":"0.1.2018.08.10"},{"date":"2024-03-20","total":4727,"delta":6,"version":"0.1.2018.08.10"},{"date":"2024-03-21","total":4729,"delta":2,"version":"0.1.2018.08.10"},{"date":"2024-03-08","total":1489,"delta":2,"version":"3.2.0"},{"date":"2024-03-09","total":1491,"delta":2,"version":"3.2.0"},{"date":"2024-03-10","total":1493,"delta":2,"version":"3.2.0"},{"date":"2024-03-11","total":1495,"delta":2,"version":"3.2.0"},{"date":"2024-03-12","total":1497,"delta":2,"version":"3.2.0"},{"date":"2024-03-13","total":1499,"delta":2,"version":"3.2.0"},{"date":"2024-03-14","total":1501,"delta":2,"version":"3.2.0"},{"date":"2024-03-15","total":1503,"delta":2,"version":"3.2.0"},{"date":"2024-03-16","total":1505,"delta":2,"version":"3.2.0"},{"date":"2024-03-17","total":1507,"delta":2,"version":"3.2.0"},{"date":"2024-03-18","total":1508,"delta":1,"version":"3.2.0"},{"date":"2024-03-19","total":1510,"delta":2,"version":"3.2.0"},{"date":"2024-03-20","total":1513,"delta":3,"version":"3.2.0"},{"date":"2024-03-21","total":1515,"delta":2,"version":"3.2.0"},{"date":"2024-03-08","total":1341,"delta":2,"version":"3.3.0"},{"date":"2024-03-09","total":1343,"delta":2,"version":"3.3.0"},{"date":"2024-03-10","total":1345,"delta":2,"version":"3.3.0"},{"date":"2024-03-11","total":1347,"delta":2,"version":"3.3.0"},{"date":"2024-03-12","total":1349,"delta":2,"version":"3.3.0"},{"date":"2024-03-13","total":1351,"delta":2,"version":"3.3.0"},{"date":"2024-03-14","total":1353,"delta":2,"version":"3.3.0"},{"date":"2024-03-15","total":1355,"delta":2,"version":"3.3.0"},{"date":"2024-03-16","total":1357,"delta":2,"version":"3.3.0"},{"date":"2024-03-17","total":1359,"delta":2,"version":"3.3.0"},{"date":"2024-03-18","total":1360,"delta":1,"version":"3.3.0"},{"date":"2024-03-19","total":1362,"delta":2,"version":"3.3.0"},{"date":"2024-03-20","total":1365,"delta":3,"version":"3.3.0"},{"date":"2024-03-21","total":1367,"delta":2,"version":"3.3.0"},{"date":"2024-03-08","total":1683,"delta":2,"version":"3.4.0"},{"date":"2024-03-09","total":1685,"delta":2,"version":"3.4.0"},{"date":"2024-03-10","total":1687,"delta":2,"version":"3.4.0"},{"date":"2024-03-11","total":1689,"delta":2,"version":"3.4.0"},{"date":"2024-03-12","total":1691,"delta":2,"version":"3.4.0"},{"date":"2024-03-13","total":1693,"delta":2,"version":"3.4.0"},{"date":"2024-03-14","total":1695,"delta":2,"version":"3.4.0"},{"date":"2024-03-15","total":1698,"delta":3,"version":"3.4.0"},{"date":"2024-03-16","total":1702,"delta":4,"version":"3.4.0"},{"date":"2024-03-17","total":1705,"delta":3,"version":"3.4.0"},{"date":"2024-03-18","total":1706,"delta":1,"version":"3.4.0"},{"date":"2024-03-19","total":1710,"delta":4,"version":"3.4.0"},{"date":"2024-03-20","total":1715,"delta":5,"version":"3.4.0"},{"date":"2024-03-21","total":1717,"delta":2,"version":"3.4.0"},{"date":"2024-03-08","total":1828,"delta":2,"version":"3.5.0"},{"date":"2024-03-09","total":1830,"delta":2,"version":"3.5.0"},{"date":"2024-03-10","total":1832,"delta":2,"version":"3.5.0"},{"date":"2024-03-11","total":1834,"delta":2,"version":"3.5.0"},{"date":"2024-03-12","total":1836,"delta":2,"version":"3.5.0"},{"date":"2024-03-13","total":1838,"delta":2,"version":"3.5.0"},{"date":"2024-03-14","total":1840,"delta":2,"version":"3.5.0"},{"date":"2024-03-15","total":1842,"delta":2,"version":"3.5.0"},{"date":"2024-03-16","total":1844,"delta":2,"version":"3.5.0"},{"date":"2024-03-17","total":1846,"delta":2,"version":"3.5.0"},{"date":"2024-03-18","total":1847,"delta":1,"version":"3.5.0"},{"date":"2024-03-19","total":1849,"delta":2,"version":"3.5.0"},{"date":"2024-03-20","total":1851,"delta":2,"version":"3.5.0"},{"date":"2024-03-21","total":1853,"delta":2,"version":"3.5.0"},{"date":"2024-03-08","total":984,"delta":3,"version":"4.0.0"},{"date":"2024-03-09","total":986,"delta":2,"version":"4.0.0"},{"date":"2024-03-10","total":988,"delta":2,"version":"4.0.0"},{"date":"2024-03-11","total":990,"delta":2,"version":"4.0.0"},{"date":"2024-03-12","total":992,"delta":2,"version":"4.0.0"},{"date":"2024-03-13","total":994,"delta":2,"version":"4.0.0"},{"date":"2024-03-14","total":997,"delta":3,"version":"4.0.0"},{"date":"2024-03-15","total":999,"delta":2,"version":"4.0.0"},{"date":"2024-03-16","total":1001,"delta":2,"version":"4.0.0"},{"date":"2024-03-17","total":1003,"delta":2,"version":"4.0.0"},{"date":"2024-03-18","total":1004,"delta":1,"version":"4.0.0"},{"date":"2024-03-19","total":1006,"delta":2,"version":"4.0.0"},{"date":"2024-03-20","total":1009,"delta":3,"version":"4.0.0"},{"date":"2024-03-21","total":1012,"delta":3,"version":"4.0.0"},{"date":"2024-03-08","total":698,"delta":2,"version":"4.1.0"},{"date":"2024-03-09","total":701,"delta":3,"version":"4.1.0"},{"date":"2024-03-10","total":703,"delta":2,"version":"4.1.0"},{"date":"2024-03-11","total":706,"delta":3,"version":"4.1.0"},{"date":"2024-03-12","total":709,"delta":3,"version":"4.1.0"},{"date":"2024-03-13","total":712,"delta":3,"version":"4.1.0"},{"date":"2024-03-14","total":715,"delta":3,"version":"4.1.0"},{"date":"2024-03-15","total":718,"delta":3,"version":"4.1.0"},{"date":"2024-03-16","total":721,"delta":3,"version":"4.1.0"},{"date":"2024-03-17","total":723,"delta":2,"version":"4.1.0"},{"date":"2024-03-18","total":725,"delta":2,"version":"4.1.0"},{"date":"2024-03-19","total":727,"delta":2,"version":"4.1.0"},{"date":"2024-03-20","total":731,"delta":4,"version":"4.1.0"},{"date":"2024-03-21","total":733,"delta":2,"version":"4.1.0"}]