[{"date":"2026-04-13","total":3398,"delta":30,"subdir":"linux-aarch64"},{"date":"2026-04-14","total":3426,"delta":28,"subdir":"linux-aarch64"},{"date":"2026-04-15","total":3452,"delta":26,"subdir":"linux-aarch64"},{"date":"2026-04-16","total":3502,"delta":50,"subdir":"linux-aarch64"},{"date":"2026-04-17","total":3535,"delta":33,"subdir":"linux-aarch64"},{"date":"2026-04-18","total":3570,"delta":35,"subdir":"linux-aarch64"},{"date":"2026-04-19","total":3610,"delta":40,"subdir":"linux-aarch64"},{"date":"2026-04-20","total":3645,"delta":35,"subdir":"linux-aarch64"},{"date":"2026-04-21","total":3681,"delta":36,"subdir":"linux-aarch64"},{"date":"2026-04-22","total":3719,"delta":38,"subdir":"linux-aarch64"},{"date":"2026-04-23","total":3751,"delta":32,"subdir":"linux-aarch64"},{"date":"2026-04-24","total":3780,"delta":29,"subdir":"linux-aarch64"},{"date":"2026-04-25","total":3812,"delta":32,"subdir":"linux-aarch64"},{"date":"2026-04-26","total":3845,"delta":33,"subdir":"linux-aarch64"},{"date":"2026-04-13","total":14218,"delta":17,"subdir":"osx-64"},{"date":"2026-04-14","total":14235,"delta":17,"subdir":"osx-64"},{"date":"2026-04-15","total":14305,"delta":70,"subdir":"osx-64"},{"date":"2026-04-16","total":14318,"delta":13,"subdir":"osx-64"},{"date":"2026-04-17","total":14331,"delta":13,"subdir":"osx-64"},{"date":"2026-04-18","total":14338,"delta":7,"subdir":"osx-64"},{"date":"2026-04-19","total":14351,"delta":13,"subdir":"osx-64"},{"date":"2026-04-20","total":14359,"delta":8,"subdir":"osx-64"},{"date":"2026-04-21","total":14365,"delta":6,"subdir":"osx-64"},{"date":"2026-04-22","total":14375,"delta":10,"subdir":"osx-64"},{"date":"2026-04-23","total":14384,"delta":9,"subdir":"osx-64"},{"date":"2026-04-24","total":14391,"delta":7,"subdir":"osx-64"},{"date":"2026-04-25","total":14406,"delta":15,"subdir":"osx-64"},{"date":"2026-04-26","total":14432,"delta":26,"subdir":"osx-64"},{"date":"2026-04-13","total":589,"delta":1,"subdir":"osx-arm64"},{"date":"2026-04-14","total":590,"delta":1,"subdir":"osx-arm64"},{"date":"2026-04-15","total":590,"delta":0,"subdir":"osx-arm64"},{"date":"2026-04-16","total":596,"delta":6,"subdir":"osx-arm64"},{"date":"2026-04-17","total":606,"delta":10,"subdir":"osx-arm64"},{"date":"2026-04-18","total":613,"delta":7,"subdir":"osx-arm64"},{"date":"2026-04-19","total":624,"delta":11,"subdir":"osx-arm64"},{"date":"2026-04-20","total":627,"delta":3,"subdir":"osx-arm64"},{"date":"2026-04-21","total":634,"delta":7,"subdir":"osx-arm64"},{"date":"2026-04-22","total":649,"delta":15,"subdir":"osx-arm64"},{"date":"2026-04-23","total":654,"delta":5,"subdir":"osx-arm64"},{"date":"2026-04-24","total":654,"delta":0,"subdir":"osx-arm64"},{"date":"2026-04-25","total":661,"delta":7,"subdir":"osx-arm64"},{"date":"2026-04-26","total":681,"delta":20,"subdir":"osx-arm64"},{"date":"2026-04-13","total":21107,"delta":105,"subdir":"linux-64"},{"date":"2026-04-14","total":21152,"delta":45,"subdir":"linux-64"},{"date":"2026-04-15","total":21199,"delta":47,"subdir":"linux-64"},{"date":"2026-04-16","total":21324,"delta":125,"subdir":"linux-64"},{"date":"2026-04-17","total":21384,"delta":60,"subdir":"linux-64"},{"date":"2026-04-18","total":21430,"delta":46,"subdir":"linux-64"},{"date":"2026-04-19","total":21521,"delta":91,"subdir":"linux-64"},{"date":"2026-04-20","total":21570,"delta":49,"subdir":"linux-64"},{"date":"2026-04-21","total":21624,"delta":54,"subdir":"linux-64"},{"date":"2026-04-22","total":21689,"delta":65,"subdir":"linux-64"},{"date":"2026-04-23","total":21764,"delta":75,"subdir":"linux-64"},{"date":"2026-04-24","total":21822,"delta":58,"subdir":"linux-64"},{"date":"2026-04-25","total":21862,"delta":40,"subdir":"linux-64"},{"date":"2026-04-26","total":21965,"delta":103,"subdir":"linux-64"}]