[{"date":"2025-10-03","total":20596,"delta":17,"subdir":"noarch"},{"date":"2025-10-04","total":20602,"delta":6,"subdir":"noarch"},{"date":"2025-10-05","total":20619,"delta":17,"subdir":"noarch"},{"date":"2025-10-06","total":20623,"delta":4,"subdir":"noarch"},{"date":"2025-10-07","total":20629,"delta":6,"subdir":"noarch"},{"date":"2025-10-08","total":20636,"delta":7,"subdir":"noarch"},{"date":"2025-10-09","total":20643,"delta":7,"subdir":"noarch"},{"date":"2025-10-10","total":20650,"delta":7,"subdir":"noarch"},{"date":"2025-10-11","total":20657,"delta":7,"subdir":"noarch"},{"date":"2025-10-12","total":20671,"delta":14,"subdir":"noarch"},{"date":"2025-10-13","total":20677,"delta":6,"subdir":"noarch"},{"date":"2025-10-14","total":20694,"delta":17,"subdir":"noarch"},{"date":"2025-10-15","total":20695,"delta":1,"subdir":"noarch"},{"date":"2025-10-16","total":20701,"delta":6,"subdir":"noarch"}]