[{"date":"2025-03-31","total":34229,"delta":1,"version":"2.64"},{"date":"2025-04-01","total":34251,"delta":22,"version":"2.64"},{"date":"2025-04-02","total":34263,"delta":12,"version":"2.64"},{"date":"2025-04-03","total":34277,"delta":14,"version":"2.64"},{"date":"2025-04-04","total":34294,"delta":17,"version":"2.64"},{"date":"2025-04-05","total":34299,"delta":5,"version":"2.64"},{"date":"2025-04-06","total":34310,"delta":11,"version":"2.64"},{"date":"2025-04-07","total":34317,"delta":7,"version":"2.64"},{"date":"2025-04-08","total":34331,"delta":14,"version":"2.64"},{"date":"2025-04-09","total":34347,"delta":16,"version":"2.64"},{"date":"2025-04-10","total":34374,"delta":27,"version":"2.64"},{"date":"2025-04-11","total":34386,"delta":12,"version":"2.64"},{"date":"2025-04-12","total":34400,"delta":14,"version":"2.64"},{"date":"2025-04-13","total":34415,"delta":15,"version":"2.64"},{"date":"2025-03-31","total":155898,"delta":3,"version":"2.84"},{"date":"2025-04-01","total":155949,"delta":51,"version":"2.84"},{"date":"2025-04-02","total":155999,"delta":50,"version":"2.84"},{"date":"2025-04-03","total":156072,"delta":73,"version":"2.84"},{"date":"2025-04-04","total":156148,"delta":76,"version":"2.84"},{"date":"2025-04-05","total":156196,"delta":48,"version":"2.84"},{"date":"2025-04-06","total":156213,"delta":17,"version":"2.84"},{"date":"2025-04-07","total":156243,"delta":30,"version":"2.84"},{"date":"2025-04-08","total":156290,"delta":47,"version":"2.84"},{"date":"2025-04-09","total":156372,"delta":82,"version":"2.84"},{"date":"2025-04-10","total":156442,"delta":70,"version":"2.84"},{"date":"2025-04-11","total":156499,"delta":57,"version":"2.84"},{"date":"2025-04-12","total":156597,"delta":98,"version":"2.84"},{"date":"2025-04-13","total":156621,"delta":24,"version":"2.84"},{"date":"2025-03-31","total":5582,"delta":0,"version":"2.86"},{"date":"2025-04-01","total":5586,"delta":4,"version":"2.86"},{"date":"2025-04-02","total":5588,"delta":2,"version":"2.86"},{"date":"2025-04-03","total":5591,"delta":3,"version":"2.86"},{"date":"2025-04-04","total":5594,"delta":3,"version":"2.86"},{"date":"2025-04-05","total":5596,"delta":2,"version":"2.86"},{"date":"2025-04-06","total":5599,"delta":3,"version":"2.86"},{"date":"2025-04-07","total":5601,"delta":2,"version":"2.86"},{"date":"2025-04-08","total":5603,"delta":2,"version":"2.86"},{"date":"2025-04-09","total":5605,"delta":2,"version":"2.86"},{"date":"2025-04-10","total":5607,"delta":2,"version":"2.86"},{"date":"2025-04-11","total":5609,"delta":2,"version":"2.86"},{"date":"2025-04-12","total":5611,"delta":2,"version":"2.86"},{"date":"2025-04-13","total":5614,"delta":3,"version":"2.86"},{"date":"2025-03-31","total":44392,"delta":5,"version":"2.87"},{"date":"2025-04-01","total":44438,"delta":46,"version":"2.87"},{"date":"2025-04-02","total":44469,"delta":31,"version":"2.87"},{"date":"2025-04-03","total":44504,"delta":35,"version":"2.87"},{"date":"2025-04-04","total":44551,"delta":47,"version":"2.87"},{"date":"2025-04-05","total":44586,"delta":35,"version":"2.87"},{"date":"2025-04-06","total":44604,"delta":18,"version":"2.87"},{"date":"2025-04-07","total":44631,"delta":27,"version":"2.87"},{"date":"2025-04-08","total":44672,"delta":41,"version":"2.87"},{"date":"2025-04-09","total":44707,"delta":35,"version":"2.87"},{"date":"2025-04-10","total":44757,"delta":50,"version":"2.87"},{"date":"2025-04-11","total":44803,"delta":46,"version":"2.87"},{"date":"2025-04-12","total":44837,"delta":34,"version":"2.87"},{"date":"2025-04-13","total":44851,"delta":14,"version":"2.87"}]