[{"date":"2024-03-08","total":3656,"delta":2,"version":"1.80.0"},{"date":"2024-03-09","total":3657,"delta":1,"version":"1.80.0"},{"date":"2024-03-10","total":3658,"delta":1,"version":"1.80.0"},{"date":"2024-03-11","total":3664,"delta":6,"version":"1.80.0"},{"date":"2024-03-12","total":3669,"delta":5,"version":"1.80.0"},{"date":"2024-03-13","total":3670,"delta":1,"version":"1.80.0"},{"date":"2024-03-14","total":3672,"delta":2,"version":"1.80.0"},{"date":"2024-03-15","total":3673,"delta":1,"version":"1.80.0"},{"date":"2024-03-16","total":3674,"delta":1,"version":"1.80.0"},{"date":"2024-03-17","total":3675,"delta":1,"version":"1.80.0"},{"date":"2024-03-18","total":3676,"delta":1,"version":"1.80.0"},{"date":"2024-03-19","total":3678,"delta":2,"version":"1.80.0"},{"date":"2024-03-20","total":3679,"delta":1,"version":"1.80.0"},{"date":"2024-03-21","total":3680,"delta":1,"version":"1.80.0"},{"date":"2024-03-08","total":6603,"delta":3,"version":"1.82.0"},{"date":"2024-03-09","total":6605,"delta":2,"version":"1.82.0"},{"date":"2024-03-10","total":6606,"delta":1,"version":"1.82.0"},{"date":"2024-03-11","total":6608,"delta":2,"version":"1.82.0"},{"date":"2024-03-12","total":6610,"delta":2,"version":"1.82.0"},{"date":"2024-03-13","total":6613,"delta":3,"version":"1.82.0"},{"date":"2024-03-14","total":6616,"delta":3,"version":"1.82.0"},{"date":"2024-03-15","total":6617,"delta":1,"version":"1.82.0"},{"date":"2024-03-16","total":6619,"delta":2,"version":"1.82.0"},{"date":"2024-03-17","total":6621,"delta":2,"version":"1.82.0"},{"date":"2024-03-18","total":6622,"delta":1,"version":"1.82.0"},{"date":"2024-03-19","total":6626,"delta":4,"version":"1.82.0"},{"date":"2024-03-20","total":6628,"delta":2,"version":"1.82.0"},{"date":"2024-03-21","total":6629,"delta":1,"version":"1.82.0"},{"date":"2024-03-08","total":2996,"delta":2,"version":"1.84.0"},{"date":"2024-03-09","total":2998,"delta":2,"version":"1.84.0"},{"date":"2024-03-10","total":3000,"delta":2,"version":"1.84.0"},{"date":"2024-03-11","total":3002,"delta":2,"version":"1.84.0"},{"date":"2024-03-12","total":3004,"delta":2,"version":"1.84.0"},{"date":"2024-03-13","total":3006,"delta":2,"version":"1.84.0"},{"date":"2024-03-14","total":3008,"delta":2,"version":"1.84.0"},{"date":"2024-03-15","total":3010,"delta":2,"version":"1.84.0"},{"date":"2024-03-16","total":3012,"delta":2,"version":"1.84.0"},{"date":"2024-03-17","total":3014,"delta":2,"version":"1.84.0"},{"date":"2024-03-18","total":3015,"delta":1,"version":"1.84.0"},{"date":"2024-03-19","total":3018,"delta":3,"version":"1.84.0"},{"date":"2024-03-20","total":3020,"delta":2,"version":"1.84.0"},{"date":"2024-03-21","total":3022,"delta":2,"version":"1.84.0"},{"date":"2024-03-08","total":4407,"delta":2,"version":"1.86.0"},{"date":"2024-03-09","total":4410,"delta":3,"version":"1.86.0"},{"date":"2024-03-10","total":4412,"delta":2,"version":"1.86.0"},{"date":"2024-03-11","total":4415,"delta":3,"version":"1.86.0"},{"date":"2024-03-12","total":4417,"delta":2,"version":"1.86.0"},{"date":"2024-03-13","total":4421,"delta":4,"version":"1.86.0"},{"date":"2024-03-14","total":4424,"delta":3,"version":"1.86.0"},{"date":"2024-03-15","total":4426,"delta":2,"version":"1.86.0"},{"date":"2024-03-16","total":4429,"delta":3,"version":"1.86.0"},{"date":"2024-03-17","total":4431,"delta":2,"version":"1.86.0"},{"date":"2024-03-18","total":4432,"delta":1,"version":"1.86.0"},{"date":"2024-03-19","total":4436,"delta":4,"version":"1.86.0"},{"date":"2024-03-20","total":4438,"delta":2,"version":"1.86.0"},{"date":"2024-03-21","total":4440,"delta":2,"version":"1.86.0"},{"date":"2024-03-08","total":3275,"delta":3,"version":"1.90.0"},{"date":"2024-03-09","total":3277,"delta":2,"version":"1.90.0"},{"date":"2024-03-10","total":3279,"delta":2,"version":"1.90.0"},{"date":"2024-03-11","total":3283,"delta":4,"version":"1.90.0"},{"date":"2024-03-12","total":3289,"delta":6,"version":"1.90.0"},{"date":"2024-03-13","total":3291,"delta":2,"version":"1.90.0"},{"date":"2024-03-14","total":3294,"delta":3,"version":"1.90.0"},{"date":"2024-03-15","total":3296,"delta":2,"version":"1.90.0"},{"date":"2024-03-16","total":3300,"delta":4,"version":"1.90.0"},{"date":"2024-03-17","total":3302,"delta":2,"version":"1.90.0"},{"date":"2024-03-18","total":3303,"delta":1,"version":"1.90.0"},{"date":"2024-03-19","total":3310,"delta":7,"version":"1.90.0"},{"date":"2024-03-20","total":3316,"delta":6,"version":"1.90.0"},{"date":"2024-03-21","total":3318,"delta":2,"version":"1.90.0"},{"date":"2024-03-08","total":1425,"delta":2,"version":"1.92.0"},{"date":"2024-03-09","total":1427,"delta":2,"version":"1.92.0"},{"date":"2024-03-10","total":1429,"delta":2,"version":"1.92.0"},{"date":"2024-03-11","total":1431,"delta":2,"version":"1.92.0"},{"date":"2024-03-12","total":1433,"delta":2,"version":"1.92.0"},{"date":"2024-03-13","total":1435,"delta":2,"version":"1.92.0"},{"date":"2024-03-14","total":1438,"delta":3,"version":"1.92.0"},{"date":"2024-03-15","total":1442,"delta":4,"version":"1.92.0"},{"date":"2024-03-16","total":1445,"delta":3,"version":"1.92.0"},{"date":"2024-03-17","total":1447,"delta":2,"version":"1.92.0"},{"date":"2024-03-18","total":1448,"delta":1,"version":"1.92.0"},{"date":"2024-03-19","total":1455,"delta":7,"version":"1.92.0"},{"date":"2024-03-20","total":1457,"delta":2,"version":"1.92.0"},{"date":"2024-03-21","total":1459,"delta":2,"version":"1.92.0"},{"date":"2024-03-08","total":614,"delta":11,"version":"1.94.0"},{"date":"2024-03-09","total":619,"delta":5,"version":"1.94.0"},{"date":"2024-03-10","total":621,"delta":2,"version":"1.94.0"},{"date":"2024-03-11","total":631,"delta":10,"version":"1.94.0"},{"date":"2024-03-12","total":636,"delta":5,"version":"1.94.0"},{"date":"2024-03-13","total":647,"delta":11,"version":"1.94.0"},{"date":"2024-03-14","total":652,"delta":5,"version":"1.94.0"},{"date":"2024-03-15","total":656,"delta":4,"version":"1.94.0"},{"date":"2024-03-16","total":660,"delta":4,"version":"1.94.0"},{"date":"2024-03-17","total":662,"delta":2,"version":"1.94.0"},{"date":"2024-03-18","total":664,"delta":2,"version":"1.94.0"},{"date":"2024-03-19","total":669,"delta":5,"version":"1.94.0"},{"date":"2024-03-20","total":671,"delta":2,"version":"1.94.0"},{"date":"2024-03-21","total":675,"delta":4,"version":"1.94.0"}]