[{"date":"2026-01-31","total":182692,"delta":23,"version":"2.48"},{"date":"2026-02-01","total":182703,"delta":11,"version":"2.48"},{"date":"2026-02-02","total":182715,"delta":12,"version":"2.48"},{"date":"2026-02-03","total":182737,"delta":22,"version":"2.48"},{"date":"2026-02-04","total":182765,"delta":28,"version":"2.48"},{"date":"2026-02-05","total":182776,"delta":11,"version":"2.48"},{"date":"2026-02-06","total":182801,"delta":25,"version":"2.48"},{"date":"2026-02-07","total":182814,"delta":13,"version":"2.48"},{"date":"2026-02-08","total":182822,"delta":8,"version":"2.48"},{"date":"2026-02-09","total":182835,"delta":13,"version":"2.48"},{"date":"2026-02-10","total":182848,"delta":13,"version":"2.48"},{"date":"2026-02-11","total":182875,"delta":27,"version":"2.48"},{"date":"2026-02-12","total":182893,"delta":18,"version":"2.48"},{"date":"2026-02-13","total":182914,"delta":21,"version":"2.48"},{"date":"2026-01-31","total":1703,"delta":0,"version":"2.49"},{"date":"2026-02-01","total":1703,"delta":0,"version":"2.49"},{"date":"2026-02-02","total":1703,"delta":0,"version":"2.49"},{"date":"2026-02-03","total":1703,"delta":0,"version":"2.49"},{"date":"2026-02-04","total":1703,"delta":0,"version":"2.49"},{"date":"2026-02-05","total":1704,"delta":1,"version":"2.49"},{"date":"2026-02-06","total":1704,"delta":0,"version":"2.49"},{"date":"2026-02-07","total":1705,"delta":1,"version":"2.49"},{"date":"2026-02-08","total":1705,"delta":0,"version":"2.49"},{"date":"2026-02-09","total":1705,"delta":0,"version":"2.49"},{"date":"2026-02-10","total":1705,"delta":0,"version":"2.49"},{"date":"2026-02-11","total":1706,"delta":1,"version":"2.49"},{"date":"2026-02-12","total":1706,"delta":0,"version":"2.49"},{"date":"2026-02-13","total":1706,"delta":0,"version":"2.49"},{"date":"2026-01-31","total":1929,"delta":0,"version":"2.50"},{"date":"2026-02-01","total":1930,"delta":1,"version":"2.50"},{"date":"2026-02-02","total":1930,"delta":0,"version":"2.50"},{"date":"2026-02-03","total":1930,"delta":0,"version":"2.50"},{"date":"2026-02-04","total":1930,"delta":0,"version":"2.50"},{"date":"2026-02-05","total":1931,"delta":1,"version":"2.50"},{"date":"2026-02-06","total":1931,"delta":0,"version":"2.50"},{"date":"2026-02-07","total":1931,"delta":0,"version":"2.50"},{"date":"2026-02-08","total":1932,"delta":1,"version":"2.50"},{"date":"2026-02-09","total":1932,"delta":0,"version":"2.50"},{"date":"2026-02-10","total":1932,"delta":0,"version":"2.50"},{"date":"2026-02-11","total":1933,"delta":1,"version":"2.50"},{"date":"2026-02-12","total":1933,"delta":0,"version":"2.50"},{"date":"2026-02-13","total":1933,"delta":0,"version":"2.50"},{"date":"2026-01-31","total":1847,"delta":0,"version":"2.51"},{"date":"2026-02-01","total":1848,"delta":1,"version":"2.51"},{"date":"2026-02-02","total":1848,"delta":0,"version":"2.51"},{"date":"2026-02-03","total":1848,"delta":0,"version":"2.51"},{"date":"2026-02-04","total":1848,"delta":0,"version":"2.51"},{"date":"2026-02-05","total":1849,"delta":1,"version":"2.51"},{"date":"2026-02-06","total":1849,"delta":0,"version":"2.51"},{"date":"2026-02-07","total":1850,"delta":1,"version":"2.51"},{"date":"2026-02-08","total":1851,"delta":1,"version":"2.51"},{"date":"2026-02-09","total":1851,"delta":0,"version":"2.51"},{"date":"2026-02-10","total":1851,"delta":0,"version":"2.51"},{"date":"2026-02-11","total":1852,"delta":1,"version":"2.51"},{"date":"2026-02-12","total":1852,"delta":0,"version":"2.51"},{"date":"2026-02-13","total":1852,"delta":0,"version":"2.51"},{"date":"2026-01-31","total":1883,"delta":0,"version":"2.53"},{"date":"2026-02-01","total":1884,"delta":1,"version":"2.53"},{"date":"2026-02-02","total":1884,"delta":0,"version":"2.53"},{"date":"2026-02-03","total":1884,"delta":0,"version":"2.53"},{"date":"2026-02-04","total":1884,"delta":0,"version":"2.53"},{"date":"2026-02-05","total":1885,"delta":1,"version":"2.53"},{"date":"2026-02-06","total":1885,"delta":0,"version":"2.53"},{"date":"2026-02-07","total":1885,"delta":0,"version":"2.53"},{"date":"2026-02-08","total":1886,"delta":1,"version":"2.53"},{"date":"2026-02-09","total":1886,"delta":0,"version":"2.53"},{"date":"2026-02-10","total":1886,"delta":0,"version":"2.53"},{"date":"2026-02-11","total":1887,"delta":1,"version":"2.53"},{"date":"2026-02-12","total":1887,"delta":0,"version":"2.53"},{"date":"2026-02-13","total":1887,"delta":0,"version":"2.53"},{"date":"2026-01-31","total":60974,"delta":157,"version":"2.84"},{"date":"2026-02-01","total":61071,"delta":97,"version":"2.84"},{"date":"2026-02-02","total":61272,"delta":201,"version":"2.84"},{"date":"2026-02-03","total":61445,"delta":173,"version":"2.84"},{"date":"2026-02-04","total":61657,"delta":212,"version":"2.84"},{"date":"2026-02-05","total":61819,"delta":162,"version":"2.84"},{"date":"2026-02-06","total":61981,"delta":162,"version":"2.84"},{"date":"2026-02-07","total":62111,"delta":130,"version":"2.84"},{"date":"2026-02-08","total":62199,"delta":88,"version":"2.84"},{"date":"2026-02-09","total":62290,"delta":91,"version":"2.84"},{"date":"2026-02-10","total":62476,"delta":186,"version":"2.84"},{"date":"2026-02-11","total":62618,"delta":142,"version":"2.84"},{"date":"2026-02-12","total":62837,"delta":219,"version":"2.84"},{"date":"2026-02-13","total":63029,"delta":192,"version":"2.84"}]