[{"date":"2024-10-13","total":5543,"delta":4,"subdir":"linux-64"},{"date":"2024-10-14","total":5543,"delta":0,"subdir":"linux-64"},{"date":"2024-10-15","total":5551,"delta":8,"subdir":"linux-64"},{"date":"2024-10-16","total":5562,"delta":11,"subdir":"linux-64"},{"date":"2024-10-17","total":5569,"delta":7,"subdir":"linux-64"},{"date":"2024-10-18","total":5579,"delta":10,"subdir":"linux-64"},{"date":"2024-10-19","total":5585,"delta":6,"subdir":"linux-64"},{"date":"2024-10-20","total":5585,"delta":0,"subdir":"linux-64"},{"date":"2024-10-21","total":5590,"delta":5,"subdir":"linux-64"},{"date":"2024-10-22","total":5623,"delta":33,"subdir":"linux-64"},{"date":"2024-10-23","total":5629,"delta":6,"subdir":"linux-64"},{"date":"2024-10-24","total":5636,"delta":7,"subdir":"linux-64"},{"date":"2024-10-25","total":5641,"delta":5,"subdir":"linux-64"},{"date":"2024-10-26","total":5645,"delta":4,"subdir":"linux-64"},{"date":"2024-10-13","total":14,"delta":0,"subdir":"osx-arm64"},{"date":"2024-10-14","total":14,"delta":0,"subdir":"osx-arm64"},{"date":"2024-10-15","total":15,"delta":1,"subdir":"osx-arm64"},{"date":"2024-10-16","total":15,"delta":0,"subdir":"osx-arm64"},{"date":"2024-10-17","total":19,"delta":4,"subdir":"osx-arm64"},{"date":"2024-10-18","total":19,"delta":0,"subdir":"osx-arm64"},{"date":"2024-10-19","total":19,"delta":0,"subdir":"osx-arm64"},{"date":"2024-10-20","total":19,"delta":0,"subdir":"osx-arm64"},{"date":"2024-10-21","total":19,"delta":0,"subdir":"osx-arm64"},{"date":"2024-10-22","total":19,"delta":0,"subdir":"osx-arm64"},{"date":"2024-10-23","total":19,"delta":0,"subdir":"osx-arm64"},{"date":"2024-10-24","total":19,"delta":0,"subdir":"osx-arm64"},{"date":"2024-10-25","total":20,"delta":1,"subdir":"osx-arm64"},{"date":"2024-10-26","total":20,"delta":0,"subdir":"osx-arm64"},{"date":"2024-10-13","total":31,"delta":0,"subdir":"linux-aarch64"},{"date":"2024-10-14","total":31,"delta":0,"subdir":"linux-aarch64"},{"date":"2024-10-15","total":31,"delta":0,"subdir":"linux-aarch64"},{"date":"2024-10-16","total":31,"delta":0,"subdir":"linux-aarch64"},{"date":"2024-10-17","total":31,"delta":0,"subdir":"linux-aarch64"},{"date":"2024-10-18","total":31,"delta":0,"subdir":"linux-aarch64"},{"date":"2024-10-19","total":31,"delta":0,"subdir":"linux-aarch64"},{"date":"2024-10-20","total":31,"delta":0,"subdir":"linux-aarch64"},{"date":"2024-10-21","total":31,"delta":0,"subdir":"linux-aarch64"},{"date":"2024-10-22","total":31,"delta":0,"subdir":"linux-aarch64"},{"date":"2024-10-23","total":31,"delta":0,"subdir":"linux-aarch64"},{"date":"2024-10-24","total":31,"delta":0,"subdir":"linux-aarch64"},{"date":"2024-10-25","total":32,"delta":1,"subdir":"linux-aarch64"},{"date":"2024-10-26","total":32,"delta":0,"subdir":"linux-aarch64"},{"date":"2024-10-13","total":18246,"delta":1,"subdir":"osx-64"},{"date":"2024-10-14","total":18246,"delta":0,"subdir":"osx-64"},{"date":"2024-10-15","total":18247,"delta":1,"subdir":"osx-64"},{"date":"2024-10-16","total":18269,"delta":22,"subdir":"osx-64"},{"date":"2024-10-17","total":18316,"delta":47,"subdir":"osx-64"},{"date":"2024-10-18","total":18338,"delta":22,"subdir":"osx-64"},{"date":"2024-10-19","total":18361,"delta":23,"subdir":"osx-64"},{"date":"2024-10-20","total":18383,"delta":22,"subdir":"osx-64"},{"date":"2024-10-21","total":18405,"delta":22,"subdir":"osx-64"},{"date":"2024-10-22","total":18405,"delta":0,"subdir":"osx-64"},{"date":"2024-10-23","total":18406,"delta":1,"subdir":"osx-64"},{"date":"2024-10-24","total":18428,"delta":22,"subdir":"osx-64"},{"date":"2024-10-25","total":18451,"delta":23,"subdir":"osx-64"},{"date":"2024-10-26","total":18474,"delta":23,"subdir":"osx-64"}]