[{"date":"2026-04-12","total":460,"delta":0,"subdir":"linux-64"},{"date":"2026-04-13","total":461,"delta":1,"subdir":"linux-64"},{"date":"2026-04-14","total":461,"delta":0,"subdir":"linux-64"},{"date":"2026-04-15","total":480,"delta":19,"subdir":"linux-64"},{"date":"2026-04-16","total":481,"delta":1,"subdir":"linux-64"},{"date":"2026-04-17","total":481,"delta":0,"subdir":"linux-64"},{"date":"2026-04-18","total":489,"delta":8,"subdir":"linux-64"},{"date":"2026-04-19","total":489,"delta":0,"subdir":"linux-64"},{"date":"2026-04-20","total":489,"delta":0,"subdir":"linux-64"},{"date":"2026-04-21","total":489,"delta":0,"subdir":"linux-64"},{"date":"2026-04-22","total":491,"delta":2,"subdir":"linux-64"},{"date":"2026-04-23","total":491,"delta":0,"subdir":"linux-64"},{"date":"2026-04-24","total":491,"delta":0,"subdir":"linux-64"},{"date":"2026-04-25","total":492,"delta":1,"subdir":"linux-64"},{"date":"2026-04-12","total":264,"delta":1,"subdir":"osx-64"},{"date":"2026-04-13","total":265,"delta":1,"subdir":"osx-64"},{"date":"2026-04-14","total":266,"delta":1,"subdir":"osx-64"},{"date":"2026-04-15","total":267,"delta":1,"subdir":"osx-64"},{"date":"2026-04-16","total":267,"delta":0,"subdir":"osx-64"},{"date":"2026-04-17","total":267,"delta":0,"subdir":"osx-64"},{"date":"2026-04-18","total":267,"delta":0,"subdir":"osx-64"},{"date":"2026-04-19","total":267,"delta":0,"subdir":"osx-64"},{"date":"2026-04-20","total":267,"delta":0,"subdir":"osx-64"},{"date":"2026-04-21","total":267,"delta":0,"subdir":"osx-64"},{"date":"2026-04-22","total":267,"delta":0,"subdir":"osx-64"},{"date":"2026-04-23","total":268,"delta":1,"subdir":"osx-64"},{"date":"2026-04-24","total":268,"delta":0,"subdir":"osx-64"},{"date":"2026-04-25","total":268,"delta":0,"subdir":"osx-64"}]