[{"date":"2026-06-08","total":42376,"delta":1,"version":"1.0.1"},{"date":"2026-06-09","total":42378,"delta":2,"version":"1.0.1"},{"date":"2026-06-10","total":42379,"delta":1,"version":"1.0.1"},{"date":"2026-06-11","total":42380,"delta":1,"version":"1.0.1"},{"date":"2026-06-12","total":42382,"delta":2,"version":"1.0.1"},{"date":"2026-06-13","total":42383,"delta":1,"version":"1.0.1"},{"date":"2026-06-14","total":42388,"delta":5,"version":"1.0.1"},{"date":"2026-06-15","total":42389,"delta":1,"version":"1.0.1"},{"date":"2026-06-16","total":42390,"delta":1,"version":"1.0.1"},{"date":"2026-06-17","total":42391,"delta":1,"version":"1.0.1"},{"date":"2026-06-18","total":42392,"delta":1,"version":"1.0.1"},{"date":"2026-06-19","total":42396,"delta":4,"version":"1.0.1"},{"date":"2026-06-20","total":42397,"delta":1,"version":"1.0.1"},{"date":"2026-06-21","total":42402,"delta":5,"version":"1.0.1"},{"date":"2026-06-08","total":21245,"delta":1,"version":"1.0.2"},{"date":"2026-06-09","total":21246,"delta":1,"version":"1.0.2"},{"date":"2026-06-10","total":21247,"delta":1,"version":"1.0.2"},{"date":"2026-06-11","total":21248,"delta":1,"version":"1.0.2"},{"date":"2026-06-12","total":21249,"delta":1,"version":"1.0.2"},{"date":"2026-06-13","total":21250,"delta":1,"version":"1.0.2"},{"date":"2026-06-14","total":21253,"delta":3,"version":"1.0.2"},{"date":"2026-06-15","total":21254,"delta":1,"version":"1.0.2"},{"date":"2026-06-16","total":21255,"delta":1,"version":"1.0.2"},{"date":"2026-06-17","total":21256,"delta":1,"version":"1.0.2"},{"date":"2026-06-18","total":21257,"delta":1,"version":"1.0.2"},{"date":"2026-06-19","total":21260,"delta":3,"version":"1.0.2"},{"date":"2026-06-20","total":21261,"delta":1,"version":"1.0.2"},{"date":"2026-06-21","total":21264,"delta":3,"version":"1.0.2"},{"date":"2026-06-08","total":10967,"delta":1,"version":"1.0.3"},{"date":"2026-06-09","total":10969,"delta":2,"version":"1.0.3"},{"date":"2026-06-10","total":10970,"delta":1,"version":"1.0.3"},{"date":"2026-06-11","total":10971,"delta":1,"version":"1.0.3"},{"date":"2026-06-12","total":10973,"delta":2,"version":"1.0.3"},{"date":"2026-06-13","total":10974,"delta":1,"version":"1.0.3"},{"date":"2026-06-14","total":10976,"delta":2,"version":"1.0.3"},{"date":"2026-06-15","total":10977,"delta":1,"version":"1.0.3"},{"date":"2026-06-16","total":10978,"delta":1,"version":"1.0.3"},{"date":"2026-06-17","total":10979,"delta":1,"version":"1.0.3"},{"date":"2026-06-18","total":10980,"delta":1,"version":"1.0.3"},{"date":"2026-06-19","total":10981,"delta":1,"version":"1.0.3"},{"date":"2026-06-20","total":10982,"delta":1,"version":"1.0.3"},{"date":"2026-06-21","total":10984,"delta":2,"version":"1.0.3"},{"date":"2026-06-08","total":8667,"delta":1,"version":"2.0.1"},{"date":"2026-06-09","total":8669,"delta":2,"version":"2.0.1"},{"date":"2026-06-10","total":8670,"delta":1,"version":"2.0.1"},{"date":"2026-06-11","total":8671,"delta":1,"version":"2.0.1"},{"date":"2026-06-12","total":8673,"delta":2,"version":"2.0.1"},{"date":"2026-06-13","total":8674,"delta":1,"version":"2.0.1"},{"date":"2026-06-14","total":8676,"delta":2,"version":"2.0.1"},{"date":"2026-06-15","total":8677,"delta":1,"version":"2.0.1"},{"date":"2026-06-16","total":8678,"delta":1,"version":"2.0.1"},{"date":"2026-06-17","total":8679,"delta":1,"version":"2.0.1"},{"date":"2026-06-18","total":8680,"delta":1,"version":"2.0.1"},{"date":"2026-06-19","total":8681,"delta":1,"version":"2.0.1"},{"date":"2026-06-20","total":8682,"delta":1,"version":"2.0.1"},{"date":"2026-06-21","total":8684,"delta":2,"version":"2.0.1"},{"date":"2026-06-08","total":63,"delta":0,"version":"2.0.2"},{"date":"2026-06-09","total":64,"delta":1,"version":"2.0.2"},{"date":"2026-06-10","total":64,"delta":0,"version":"2.0.2"},{"date":"2026-06-11","total":64,"delta":0,"version":"2.0.2"},{"date":"2026-06-12","total":66,"delta":2,"version":"2.0.2"},{"date":"2026-06-13","total":67,"delta":1,"version":"2.0.2"},{"date":"2026-06-14","total":68,"delta":1,"version":"2.0.2"},{"date":"2026-06-15","total":68,"delta":0,"version":"2.0.2"},{"date":"2026-06-16","total":68,"delta":0,"version":"2.0.2"},{"date":"2026-06-17","total":69,"delta":1,"version":"2.0.2"},{"date":"2026-06-18","total":69,"delta":0,"version":"2.0.2"},{"date":"2026-06-19","total":70,"delta":1,"version":"2.0.2"},{"date":"2026-06-20","total":70,"delta":0,"version":"2.0.2"},{"date":"2026-06-21","total":72,"delta":2,"version":"2.0.2"}]