[{"date":"2024-02-05","total":3822,"delta":2,"version":"1.0.1"},{"date":"2024-02-06","total":3824,"delta":2,"version":"1.0.1"},{"date":"2024-02-07","total":3826,"delta":2,"version":"1.0.1"},{"date":"2024-02-08","total":3828,"delta":2,"version":"1.0.1"},{"date":"2024-02-09","total":3830,"delta":2,"version":"1.0.1"},{"date":"2024-02-10","total":3835,"delta":5,"version":"1.0.1"},{"date":"2024-02-11","total":3837,"delta":2,"version":"1.0.1"},{"date":"2024-02-12","total":3842,"delta":5,"version":"1.0.1"},{"date":"2024-02-13","total":3847,"delta":5,"version":"1.0.1"},{"date":"2024-02-14","total":3849,"delta":2,"version":"1.0.1"},{"date":"2024-02-15","total":3852,"delta":3,"version":"1.0.1"},{"date":"2024-02-16","total":3857,"delta":5,"version":"1.0.1"},{"date":"2024-02-17","total":3859,"delta":2,"version":"1.0.1"},{"date":"2024-02-18","total":3861,"delta":2,"version":"1.0.1"},{"date":"2024-02-05","total":1171,"delta":2,"version":"1.0.2"},{"date":"2024-02-06","total":1173,"delta":2,"version":"1.0.2"},{"date":"2024-02-07","total":1175,"delta":2,"version":"1.0.2"},{"date":"2024-02-08","total":1177,"delta":2,"version":"1.0.2"},{"date":"2024-02-09","total":1179,"delta":2,"version":"1.0.2"},{"date":"2024-02-10","total":1181,"delta":2,"version":"1.0.2"},{"date":"2024-02-11","total":1183,"delta":2,"version":"1.0.2"},{"date":"2024-02-12","total":1187,"delta":4,"version":"1.0.2"},{"date":"2024-02-13","total":1191,"delta":4,"version":"1.0.2"},{"date":"2024-02-14","total":1193,"delta":2,"version":"1.0.2"},{"date":"2024-02-15","total":1195,"delta":2,"version":"1.0.2"},{"date":"2024-02-16","total":1199,"delta":4,"version":"1.0.2"},{"date":"2024-02-17","total":1201,"delta":2,"version":"1.0.2"},{"date":"2024-02-18","total":1203,"delta":2,"version":"1.0.2"}]