[{"date":"2024-06-09","total":132993,"delta":17,"version":"0.63"},{"date":"2024-06-10","total":133015,"delta":22,"version":"0.63"},{"date":"2024-06-11","total":133053,"delta":38,"version":"0.63"},{"date":"2024-06-12","total":133115,"delta":62,"version":"0.63"},{"date":"2024-06-13","total":133181,"delta":66,"version":"0.63"},{"date":"2024-06-14","total":133237,"delta":56,"version":"0.63"},{"date":"2024-06-15","total":133289,"delta":52,"version":"0.63"},{"date":"2024-06-16","total":133311,"delta":22,"version":"0.63"},{"date":"2024-06-17","total":133342,"delta":31,"version":"0.63"},{"date":"2024-06-18","total":133388,"delta":46,"version":"0.63"},{"date":"2024-06-19","total":133431,"delta":43,"version":"0.63"},{"date":"2024-06-20","total":133494,"delta":63,"version":"0.63"},{"date":"2024-06-21","total":133561,"delta":67,"version":"0.63"},{"date":"2024-06-22","total":133608,"delta":47,"version":"0.63"}]