[{"date":"2024-07-03","total":2218,"delta":2,"version":"1.0.0"},{"date":"2024-07-04","total":2220,"delta":2,"version":"1.0.0"},{"date":"2024-07-05","total":2222,"delta":2,"version":"1.0.0"},{"date":"2024-07-06","total":2224,"delta":2,"version":"1.0.0"},{"date":"2024-07-07","total":2226,"delta":2,"version":"1.0.0"},{"date":"2024-07-08","total":2228,"delta":2,"version":"1.0.0"},{"date":"2024-07-09","total":2230,"delta":2,"version":"1.0.0"},{"date":"2024-07-10","total":2232,"delta":2,"version":"1.0.0"},{"date":"2024-07-11","total":2234,"delta":2,"version":"1.0.0"},{"date":"2024-07-12","total":2236,"delta":2,"version":"1.0.0"},{"date":"2024-07-13","total":2238,"delta":2,"version":"1.0.0"},{"date":"2024-07-14","total":2240,"delta":2,"version":"1.0.0"},{"date":"2024-07-15","total":2244,"delta":4,"version":"1.0.0"},{"date":"2024-07-16","total":2248,"delta":4,"version":"1.0.0"},{"date":"2024-07-03","total":2050,"delta":2,"version":"1.2.0"},{"date":"2024-07-04","total":2052,"delta":2,"version":"1.2.0"},{"date":"2024-07-05","total":2054,"delta":2,"version":"1.2.0"},{"date":"2024-07-06","total":2056,"delta":2,"version":"1.2.0"},{"date":"2024-07-07","total":2058,"delta":2,"version":"1.2.0"},{"date":"2024-07-08","total":2060,"delta":2,"version":"1.2.0"},{"date":"2024-07-09","total":2062,"delta":2,"version":"1.2.0"},{"date":"2024-07-10","total":2064,"delta":2,"version":"1.2.0"},{"date":"2024-07-11","total":2066,"delta":2,"version":"1.2.0"},{"date":"2024-07-12","total":2068,"delta":2,"version":"1.2.0"},{"date":"2024-07-13","total":2070,"delta":2,"version":"1.2.0"},{"date":"2024-07-14","total":2072,"delta":2,"version":"1.2.0"},{"date":"2024-07-15","total":2075,"delta":3,"version":"1.2.0"},{"date":"2024-07-16","total":2078,"delta":3,"version":"1.2.0"},{"date":"2024-07-03","total":1899,"delta":2,"version":"1.4.0"},{"date":"2024-07-04","total":1901,"delta":2,"version":"1.4.0"},{"date":"2024-07-05","total":1903,"delta":2,"version":"1.4.0"},{"date":"2024-07-06","total":1905,"delta":2,"version":"1.4.0"},{"date":"2024-07-07","total":1907,"delta":2,"version":"1.4.0"},{"date":"2024-07-08","total":1909,"delta":2,"version":"1.4.0"},{"date":"2024-07-09","total":1911,"delta":2,"version":"1.4.0"},{"date":"2024-07-10","total":1913,"delta":2,"version":"1.4.0"},{"date":"2024-07-11","total":1915,"delta":2,"version":"1.4.0"},{"date":"2024-07-12","total":1917,"delta":2,"version":"1.4.0"},{"date":"2024-07-13","total":1919,"delta":2,"version":"1.4.0"},{"date":"2024-07-14","total":1921,"delta":2,"version":"1.4.0"},{"date":"2024-07-15","total":1924,"delta":3,"version":"1.4.0"},{"date":"2024-07-16","total":1927,"delta":3,"version":"1.4.0"},{"date":"2024-07-03","total":1247,"delta":2,"version":"1.8.0"},{"date":"2024-07-04","total":1249,"delta":2,"version":"1.8.0"},{"date":"2024-07-05","total":1251,"delta":2,"version":"1.8.0"},{"date":"2024-07-06","total":1253,"delta":2,"version":"1.8.0"},{"date":"2024-07-07","total":1255,"delta":2,"version":"1.8.0"},{"date":"2024-07-08","total":1257,"delta":2,"version":"1.8.0"},{"date":"2024-07-09","total":1259,"delta":2,"version":"1.8.0"},{"date":"2024-07-10","total":1261,"delta":2,"version":"1.8.0"},{"date":"2024-07-11","total":1263,"delta":2,"version":"1.8.0"},{"date":"2024-07-12","total":1265,"delta":2,"version":"1.8.0"},{"date":"2024-07-13","total":1267,"delta":2,"version":"1.8.0"},{"date":"2024-07-14","total":1269,"delta":2,"version":"1.8.0"},{"date":"2024-07-15","total":1272,"delta":3,"version":"1.8.0"},{"date":"2024-07-16","total":1275,"delta":3,"version":"1.8.0"},{"date":"2024-07-03","total":733,"delta":2,"version":"1.10.0"},{"date":"2024-07-04","total":735,"delta":2,"version":"1.10.0"},{"date":"2024-07-05","total":737,"delta":2,"version":"1.10.0"},{"date":"2024-07-06","total":739,"delta":2,"version":"1.10.0"},{"date":"2024-07-07","total":741,"delta":2,"version":"1.10.0"},{"date":"2024-07-08","total":743,"delta":2,"version":"1.10.0"},{"date":"2024-07-09","total":745,"delta":2,"version":"1.10.0"},{"date":"2024-07-10","total":747,"delta":2,"version":"1.10.0"},{"date":"2024-07-11","total":749,"delta":2,"version":"1.10.0"},{"date":"2024-07-12","total":751,"delta":2,"version":"1.10.0"},{"date":"2024-07-13","total":753,"delta":2,"version":"1.10.0"},{"date":"2024-07-14","total":755,"delta":2,"version":"1.10.0"},{"date":"2024-07-15","total":758,"delta":3,"version":"1.10.0"},{"date":"2024-07-16","total":761,"delta":3,"version":"1.10.0"}]