[{"date": "2022-02-07", "total": 705, "delta": 2, "version": "20201223"}, {"date": "2022-02-08", "total": 707, "delta": 2, "version": "20201223"}, {"date": "2022-02-09", "total": 709, "delta": 2, "version": "20201223"}, {"date": "2022-02-10", "total": 711, "delta": 2, "version": "20201223"}, {"date": "2022-02-11", "total": 713, "delta": 2, "version": "20201223"}, {"date": "2022-02-12", "total": 719, "delta": 6, "version": "20201223"}, {"date": "2022-02-13", "total": 721, "delta": 2, "version": "20201223"}, {"date": "2022-02-14", "total": 723, "delta": 2, "version": "20201223"}, {"date": "2022-02-15", "total": 725, "delta": 2, "version": "20201223"}, {"date": "2022-02-17", "total": 729, "delta": 4, "version": "20201223"}, {"date": "2022-02-20", "total": 735, "delta": 6, "version": "20201223"}, {"date": "2022-02-21", "total": 737, "delta": 2, "version": "20201223"}, {"date": "2022-02-22", "total": 744, "delta": 7, "version": "20201223"}, {"date": "2022-02-26", "total": 753, "delta": 9, "version": "20201223"}]