[{"date":"2023-09-14","total":14608,"delta":6,"version":"0.4.10"},{"date":"2023-09-15","total":14610,"delta":2,"version":"0.4.10"},{"date":"2023-09-16","total":14613,"delta":3,"version":"0.4.10"},{"date":"2023-09-17","total":14615,"delta":2,"version":"0.4.10"},{"date":"2023-09-18","total":14617,"delta":2,"version":"0.4.10"},{"date":"2023-09-19","total":14620,"delta":3,"version":"0.4.10"},{"date":"2023-09-20","total":14627,"delta":7,"version":"0.4.10"},{"date":"2023-09-21","total":14632,"delta":5,"version":"0.4.10"},{"date":"2023-09-22","total":14634,"delta":2,"version":"0.4.10"},{"date":"2023-09-23","total":14638,"delta":4,"version":"0.4.10"},{"date":"2023-09-24","total":14641,"delta":3,"version":"0.4.10"},{"date":"2023-09-25","total":14644,"delta":3,"version":"0.4.10"},{"date":"2023-09-26","total":14649,"delta":5,"version":"0.4.10"},{"date":"2023-09-27","total":14652,"delta":3,"version":"0.4.10"}]