[{"date":"2024-09-26","total":38144,"delta":50,"subdir":"noarch"},{"date":"2024-09-27","total":38218,"delta":74,"subdir":"noarch"},{"date":"2024-09-28","total":38275,"delta":57,"subdir":"noarch"},{"date":"2024-09-29","total":38355,"delta":80,"subdir":"noarch"},{"date":"2024-09-30","total":38395,"delta":40,"subdir":"noarch"},{"date":"2024-10-01","total":38435,"delta":40,"subdir":"noarch"},{"date":"2024-10-02","total":38491,"delta":56,"subdir":"noarch"},{"date":"2024-10-03","total":38546,"delta":55,"subdir":"noarch"},{"date":"2024-10-04","total":38585,"delta":39,"subdir":"noarch"},{"date":"2024-10-05","total":38638,"delta":53,"subdir":"noarch"},{"date":"2024-10-06","total":38675,"delta":37,"subdir":"noarch"},{"date":"2024-10-07","total":38747,"delta":72,"subdir":"noarch"},{"date":"2024-10-08","total":38797,"delta":50,"subdir":"noarch"},{"date":"2024-10-09","total":38803,"delta":6,"subdir":"noarch"}]