[{"date":"2024-07-07","total":1958,"delta":1,"version":"2021.11.09"},{"date":"2024-07-08","total":1959,"delta":1,"version":"2021.11.09"},{"date":"2024-07-09","total":1960,"delta":1,"version":"2021.11.09"},{"date":"2024-07-10","total":1961,"delta":1,"version":"2021.11.09"},{"date":"2024-07-11","total":1962,"delta":1,"version":"2021.11.09"},{"date":"2024-07-12","total":1964,"delta":2,"version":"2021.11.09"},{"date":"2024-07-13","total":1965,"delta":1,"version":"2021.11.09"},{"date":"2024-07-14","total":1966,"delta":1,"version":"2021.11.09"},{"date":"2024-07-15","total":1968,"delta":2,"version":"2021.11.09"},{"date":"2024-07-16","total":1970,"delta":2,"version":"2021.11.09"},{"date":"2024-07-17","total":1971,"delta":1,"version":"2021.11.09"},{"date":"2024-07-18","total":1972,"delta":1,"version":"2021.11.09"},{"date":"2024-07-19","total":1973,"delta":1,"version":"2021.11.09"},{"date":"2024-07-20","total":1974,"delta":1,"version":"2021.11.09"},{"date":"2024-07-07","total":2066,"delta":1,"version":"2021.11.18"},{"date":"2024-07-08","total":2067,"delta":1,"version":"2021.11.18"},{"date":"2024-07-09","total":2068,"delta":1,"version":"2021.11.18"},{"date":"2024-07-10","total":2069,"delta":1,"version":"2021.11.18"},{"date":"2024-07-11","total":2070,"delta":1,"version":"2021.11.18"},{"date":"2024-07-12","total":2072,"delta":2,"version":"2021.11.18"},{"date":"2024-07-13","total":2073,"delta":1,"version":"2021.11.18"},{"date":"2024-07-14","total":2074,"delta":1,"version":"2021.11.18"},{"date":"2024-07-15","total":2076,"delta":2,"version":"2021.11.18"},{"date":"2024-07-16","total":2078,"delta":2,"version":"2021.11.18"},{"date":"2024-07-17","total":2079,"delta":1,"version":"2021.11.18"},{"date":"2024-07-18","total":2080,"delta":1,"version":"2021.11.18"},{"date":"2024-07-19","total":2081,"delta":1,"version":"2021.11.18"},{"date":"2024-07-20","total":2082,"delta":1,"version":"2021.11.18"},{"date":"2024-07-07","total":2278,"delta":1,"version":"2021.11.25"},{"date":"2024-07-08","total":2279,"delta":1,"version":"2021.11.25"},{"date":"2024-07-09","total":2280,"delta":1,"version":"2021.11.25"},{"date":"2024-07-10","total":2281,"delta":1,"version":"2021.11.25"},{"date":"2024-07-11","total":2282,"delta":1,"version":"2021.11.25"},{"date":"2024-07-12","total":2284,"delta":2,"version":"2021.11.25"},{"date":"2024-07-13","total":2285,"delta":1,"version":"2021.11.25"},{"date":"2024-07-14","total":2286,"delta":1,"version":"2021.11.25"},{"date":"2024-07-15","total":2288,"delta":2,"version":"2021.11.25"},{"date":"2024-07-16","total":2290,"delta":2,"version":"2021.11.25"},{"date":"2024-07-17","total":2291,"delta":1,"version":"2021.11.25"},{"date":"2024-07-18","total":2292,"delta":1,"version":"2021.11.25"},{"date":"2024-07-19","total":2293,"delta":1,"version":"2021.11.25"},{"date":"2024-07-20","total":2294,"delta":1,"version":"2021.11.25"},{"date":"2024-07-07","total":2706,"delta":2,"version":"2021.12.06"},{"date":"2024-07-08","total":2708,"delta":2,"version":"2021.12.06"},{"date":"2024-07-09","total":2710,"delta":2,"version":"2021.12.06"},{"date":"2024-07-10","total":2712,"delta":2,"version":"2021.12.06"},{"date":"2024-07-11","total":2714,"delta":2,"version":"2021.12.06"},{"date":"2024-07-12","total":2716,"delta":2,"version":"2021.12.06"},{"date":"2024-07-13","total":2718,"delta":2,"version":"2021.12.06"},{"date":"2024-07-14","total":2720,"delta":2,"version":"2021.12.06"},{"date":"2024-07-15","total":2723,"delta":3,"version":"2021.12.06"},{"date":"2024-07-16","total":2726,"delta":3,"version":"2021.12.06"},{"date":"2024-07-17","total":2728,"delta":2,"version":"2021.12.06"},{"date":"2024-07-18","total":2730,"delta":2,"version":"2021.12.06"},{"date":"2024-07-19","total":2732,"delta":2,"version":"2021.12.06"},{"date":"2024-07-20","total":2734,"delta":2,"version":"2021.12.06"},{"date":"2024-07-07","total":2058,"delta":1,"version":"2022.01.20"},{"date":"2024-07-08","total":2060,"delta":2,"version":"2022.01.20"},{"date":"2024-07-09","total":2062,"delta":2,"version":"2022.01.20"},{"date":"2024-07-10","total":2064,"delta":2,"version":"2022.01.20"},{"date":"2024-07-11","total":2066,"delta":2,"version":"2022.01.20"},{"date":"2024-07-12","total":2068,"delta":2,"version":"2022.01.20"},{"date":"2024-07-13","total":2070,"delta":2,"version":"2022.01.20"},{"date":"2024-07-14","total":2072,"delta":2,"version":"2022.01.20"},{"date":"2024-07-15","total":2075,"delta":3,"version":"2022.01.20"},{"date":"2024-07-16","total":2078,"delta":3,"version":"2022.01.20"},{"date":"2024-07-17","total":2080,"delta":2,"version":"2022.01.20"},{"date":"2024-07-18","total":2082,"delta":2,"version":"2022.01.20"},{"date":"2024-07-19","total":2084,"delta":2,"version":"2022.01.20"},{"date":"2024-07-20","total":2086,"delta":2,"version":"2022.01.20"},{"date":"2024-07-07","total":2944,"delta":2,"version":"2022.02.02"},{"date":"2024-07-08","total":2946,"delta":2,"version":"2022.02.02"},{"date":"2024-07-09","total":2948,"delta":2,"version":"2022.02.02"},{"date":"2024-07-10","total":2950,"delta":2,"version":"2022.02.02"},{"date":"2024-07-11","total":2952,"delta":2,"version":"2022.02.02"},{"date":"2024-07-12","total":2954,"delta":2,"version":"2022.02.02"},{"date":"2024-07-13","total":2956,"delta":2,"version":"2022.02.02"},{"date":"2024-07-14","total":2958,"delta":2,"version":"2022.02.02"},{"date":"2024-07-15","total":2961,"delta":3,"version":"2022.02.02"},{"date":"2024-07-16","total":2964,"delta":3,"version":"2022.02.02"},{"date":"2024-07-17","total":2966,"delta":2,"version":"2022.02.02"},{"date":"2024-07-18","total":2968,"delta":2,"version":"2022.02.02"},{"date":"2024-07-19","total":2970,"delta":2,"version":"2022.02.02"},{"date":"2024-07-20","total":2972,"delta":2,"version":"2022.02.02"},{"date":"2024-07-07","total":7035,"delta":2,"version":"2022.03.22"},{"date":"2024-07-08","total":7037,"delta":2,"version":"2022.03.22"},{"date":"2024-07-09","total":7039,"delta":2,"version":"2022.03.22"},{"date":"2024-07-10","total":7041,"delta":2,"version":"2022.03.22"},{"date":"2024-07-11","total":7043,"delta":2,"version":"2022.03.22"},{"date":"2024-07-12","total":7045,"delta":2,"version":"2022.03.22"},{"date":"2024-07-13","total":7047,"delta":2,"version":"2022.03.22"},{"date":"2024-07-14","total":7049,"delta":2,"version":"2022.03.22"},{"date":"2024-07-15","total":7052,"delta":3,"version":"2022.03.22"},{"date":"2024-07-16","total":7055,"delta":3,"version":"2022.03.22"},{"date":"2024-07-17","total":7058,"delta":3,"version":"2022.03.22"},{"date":"2024-07-18","total":7061,"delta":3,"version":"2022.03.22"},{"date":"2024-07-19","total":7064,"delta":3,"version":"2022.03.22"},{"date":"2024-07-20","total":7066,"delta":2,"version":"2022.03.22"}]