[{"date": "2022-02-09", "total": 363, "delta": 0, "version": "2.0.3"}, {"date": "2022-02-10", "total": 365, "delta": 2, "version": "2.0.3"}, {"date": "2022-02-11", "total": 367, "delta": 2, "version": "2.0.3"}, {"date": "2022-02-12", "total": 371, "delta": 4, "version": "2.0.3"}, {"date": "2022-02-13", "total": 373, "delta": 2, "version": "2.0.3"}, {"date": "2022-02-14", "total": 375, "delta": 2, "version": "2.0.3"}, {"date": "2022-02-15", "total": 375, "delta": 0, "version": "2.0.3"}, {"date": "2022-02-17", "total": 379, "delta": 4, "version": "2.0.3"}, {"date": "2022-02-20", "total": 386, "delta": 7, "version": "2.0.3"}, {"date": "2022-02-21", "total": 386, "delta": 0, "version": "2.0.3"}, {"date": "2022-02-22", "total": 388, "delta": 2, "version": "2.0.3"}, {"date": "2022-02-26", "total": 395, "delta": 7, "version": "2.0.3"}, {"date": "2022-03-02", "total": 400, "delta": 5, "version": "2.0.3"}, {"date": "2022-03-04", "total": 402, "delta": 2, "version": "2.0.3"}, {"date": "2022-02-09", "total": 362, "delta": 0, "version": "2.0.4"}, {"date": "2022-02-10", "total": 364, "delta": 2, "version": "2.0.4"}, {"date": "2022-02-11", "total": 366, "delta": 2, "version": "2.0.4"}, {"date": "2022-02-12", "total": 371, "delta": 5, "version": "2.0.4"}, {"date": "2022-02-13", "total": 373, "delta": 2, "version": "2.0.4"}, {"date": "2022-02-14", "total": 375, "delta": 2, "version": "2.0.4"}, {"date": "2022-02-15", "total": 375, "delta": 0, "version": "2.0.4"}, {"date": "2022-02-17", "total": 379, "delta": 4, "version": "2.0.4"}, {"date": "2022-02-20", "total": 386, "delta": 7, "version": "2.0.4"}, {"date": "2022-02-21", "total": 386, "delta": 0, "version": "2.0.4"}, {"date": "2022-02-22", "total": 388, "delta": 2, "version": "2.0.4"}, {"date": "2022-02-26", "total": 395, "delta": 7, "version": "2.0.4"}, {"date": "2022-03-02", "total": 400, "delta": 5, "version": "2.0.4"}, {"date": "2022-03-04", "total": 402, "delta": 2, "version": "2.0.4"}, {"date": "2022-02-09", "total": 449, "delta": 0, "version": "2.0.5"}, {"date": "2022-02-10", "total": 451, "delta": 2, "version": "2.0.5"}, {"date": "2022-02-11", "total": 453, "delta": 2, "version": "2.0.5"}, {"date": "2022-02-12", "total": 457, "delta": 4, "version": "2.0.5"}, {"date": "2022-02-13", "total": 459, "delta": 2, "version": "2.0.5"}, {"date": "2022-02-14", "total": 461, "delta": 2, "version": "2.0.5"}, {"date": "2022-02-15", "total": 461, "delta": 0, "version": "2.0.5"}, {"date": "2022-02-17", "total": 465, "delta": 4, "version": "2.0.5"}, {"date": "2022-02-20", "total": 472, "delta": 7, "version": "2.0.5"}, {"date": "2022-02-21", "total": 472, "delta": 0, "version": "2.0.5"}, {"date": "2022-02-22", "total": 473, "delta": 1, "version": "2.0.5"}, {"date": "2022-02-26", "total": 480, "delta": 7, "version": "2.0.5"}, {"date": "2022-03-02", "total": 485, "delta": 5, "version": "2.0.5"}, {"date": "2022-03-04", "total": 487, "delta": 2, "version": "2.0.5"}, {"date": "2022-02-09", "total": 472, "delta": 0, "version": "2.0.6"}, {"date": "2022-02-10", "total": 474, "delta": 2, "version": "2.0.6"}, {"date": "2022-02-11", "total": 476, "delta": 2, "version": "2.0.6"}, {"date": "2022-02-12", "total": 480, "delta": 4, "version": "2.0.6"}, {"date": "2022-02-13", "total": 482, "delta": 2, "version": "2.0.6"}, {"date": "2022-02-14", "total": 484, "delta": 2, "version": "2.0.6"}, {"date": "2022-02-15", "total": 484, "delta": 0, "version": "2.0.6"}, {"date": "2022-02-17", "total": 488, "delta": 4, "version": "2.0.6"}, {"date": "2022-02-20", "total": 495, "delta": 7, "version": "2.0.6"}, {"date": "2022-02-21", "total": 495, "delta": 0, "version": "2.0.6"}, {"date": "2022-02-22", "total": 497, "delta": 2, "version": "2.0.6"}, {"date": "2022-02-26", "total": 504, "delta": 7, "version": "2.0.6"}, {"date": "2022-03-02", "total": 509, "delta": 5, "version": "2.0.6"}, {"date": "2022-03-04", "total": 511, "delta": 2, "version": "2.0.6"}, {"date": "2022-02-09", "total": 371, "delta": 0, "version": "2.0.7"}, {"date": "2022-02-10", "total": 373, "delta": 2, "version": "2.0.7"}, {"date": "2022-02-11", "total": 375, "delta": 2, "version": "2.0.7"}, {"date": "2022-02-12", "total": 380, "delta": 5, "version": "2.0.7"}, {"date": "2022-02-13", "total": 382, "delta": 2, "version": "2.0.7"}, {"date": "2022-02-14", "total": 384, "delta": 2, "version": "2.0.7"}, {"date": "2022-02-15", "total": 384, "delta": 0, "version": "2.0.7"}, {"date": "2022-02-17", "total": 388, "delta": 4, "version": "2.0.7"}, {"date": "2022-02-20", "total": 395, "delta": 7, "version": "2.0.7"}, {"date": "2022-02-21", "total": 395, "delta": 0, "version": "2.0.7"}, {"date": "2022-02-22", "total": 396, "delta": 1, "version": "2.0.7"}, {"date": "2022-02-26", "total": 403, "delta": 7, "version": "2.0.7"}, {"date": "2022-03-02", "total": 408, "delta": 5, "version": "2.0.7"}, {"date": "2022-03-04", "total": 410, "delta": 2, "version": "2.0.7"}, {"date": "2022-02-09", "total": 509, "delta": 0, "version": "2.1.0"}, {"date": "2022-02-10", "total": 511, "delta": 2, "version": "2.1.0"}, {"date": "2022-02-11", "total": 513, "delta": 2, "version": "2.1.0"}, {"date": "2022-02-12", "total": 517, "delta": 4, "version": "2.1.0"}, {"date": "2022-02-13", "total": 519, "delta": 2, "version": "2.1.0"}, {"date": "2022-02-14", "total": 521, "delta": 2, "version": "2.1.0"}, {"date": "2022-02-15", "total": 521, "delta": 0, "version": "2.1.0"}, {"date": "2022-02-17", "total": 525, "delta": 4, "version": "2.1.0"}, {"date": "2022-02-20", "total": 532, "delta": 7, "version": "2.1.0"}, {"date": "2022-02-21", "total": 532, "delta": 0, "version": "2.1.0"}, {"date": "2022-02-22", "total": 533, "delta": 1, "version": "2.1.0"}, {"date": "2022-02-26", "total": 540, "delta": 7, "version": "2.1.0"}, {"date": "2022-03-02", "total": 545, "delta": 5, "version": "2.1.0"}, {"date": "2022-03-04", "total": 549, "delta": 4, "version": "2.1.0"}, {"date": "2022-02-09", "total": 574, "delta": 1, "version": "2.1.1"}, {"date": "2022-02-10", "total": 576, "delta": 2, "version": "2.1.1"}, {"date": "2022-02-11", "total": 578, "delta": 2, "version": "2.1.1"}, {"date": "2022-02-12", "total": 582, "delta": 4, "version": "2.1.1"}, {"date": "2022-02-13", "total": 584, "delta": 2, "version": "2.1.1"}, {"date": "2022-02-14", "total": 586, "delta": 2, "version": "2.1.1"}, {"date": "2022-02-15", "total": 587, "delta": 1, "version": "2.1.1"}, {"date": "2022-02-17", "total": 591, "delta": 4, "version": "2.1.1"}, {"date": "2022-02-20", "total": 598, "delta": 7, "version": "2.1.1"}, {"date": "2022-02-21", "total": 598, "delta": 0, "version": "2.1.1"}, {"date": "2022-02-22", "total": 600, "delta": 2, "version": "2.1.1"}, {"date": "2022-02-26", "total": 608, "delta": 8, "version": "2.1.1"}, {"date": "2022-03-02", "total": 613, "delta": 5, "version": "2.1.1"}, {"date": "2022-03-04", "total": 615, "delta": 2, "version": "2.1.1"}]