[{"date":"2025-10-31","total":6963,"delta":1,"version":"1.1.173"},{"date":"2025-11-01","total":6964,"delta":1,"version":"1.1.173"},{"date":"2025-11-02","total":6968,"delta":4,"version":"1.1.173"},{"date":"2025-11-03","total":6969,"delta":1,"version":"1.1.173"},{"date":"2025-11-04","total":6970,"delta":1,"version":"1.1.173"},{"date":"2025-11-05","total":6971,"delta":1,"version":"1.1.173"},{"date":"2025-11-06","total":6972,"delta":1,"version":"1.1.173"},{"date":"2025-11-07","total":6974,"delta":2,"version":"1.1.173"},{"date":"2025-11-08","total":6980,"delta":6,"version":"1.1.173"},{"date":"2025-11-09","total":6985,"delta":5,"version":"1.1.173"},{"date":"2025-11-10","total":6985,"delta":0,"version":"1.1.173"},{"date":"2025-11-11","total":6987,"delta":2,"version":"1.1.173"},{"date":"2025-11-12","total":6988,"delta":1,"version":"1.1.173"},{"date":"2025-11-13","total":6989,"delta":1,"version":"1.1.173"},{"date":"2025-10-31","total":7454,"delta":1,"version":"1.1.180"},{"date":"2025-11-01","total":7455,"delta":1,"version":"1.1.180"},{"date":"2025-11-02","total":7460,"delta":5,"version":"1.1.180"},{"date":"2025-11-03","total":7461,"delta":1,"version":"1.1.180"},{"date":"2025-11-04","total":7462,"delta":1,"version":"1.1.180"},{"date":"2025-11-05","total":7463,"delta":1,"version":"1.1.180"},{"date":"2025-11-06","total":7464,"delta":1,"version":"1.1.180"},{"date":"2025-11-07","total":7466,"delta":2,"version":"1.1.180"},{"date":"2025-11-08","total":7472,"delta":6,"version":"1.1.180"},{"date":"2025-11-09","total":7480,"delta":8,"version":"1.1.180"},{"date":"2025-11-10","total":7480,"delta":0,"version":"1.1.180"},{"date":"2025-11-11","total":7482,"delta":2,"version":"1.1.180"},{"date":"2025-11-12","total":7483,"delta":1,"version":"1.1.180"},{"date":"2025-11-13","total":7485,"delta":2,"version":"1.1.180"}]