[{"date":"2024-04-03","total":1936,"delta":0,"version":"1.8.0"},{"date":"2024-04-04","total":1936,"delta":0,"version":"1.8.0"},{"date":"2024-04-05","total":1938,"delta":2,"version":"1.8.0"},{"date":"2024-04-06","total":1942,"delta":4,"version":"1.8.0"},{"date":"2024-04-07","total":1942,"delta":0,"version":"1.8.0"},{"date":"2024-04-08","total":1944,"delta":2,"version":"1.8.0"},{"date":"2024-04-09","total":1949,"delta":5,"version":"1.8.0"},{"date":"2024-04-10","total":1951,"delta":2,"version":"1.8.0"},{"date":"2024-04-11","total":1953,"delta":2,"version":"1.8.0"},{"date":"2024-04-12","total":1953,"delta":0,"version":"1.8.0"},{"date":"2024-04-13","total":1954,"delta":1,"version":"1.8.0"},{"date":"2024-04-14","total":1956,"delta":2,"version":"1.8.0"},{"date":"2024-04-15","total":1958,"delta":2,"version":"1.8.0"},{"date":"2024-04-16","total":1962,"delta":4,"version":"1.8.0"},{"date":"2024-04-03","total":1887,"delta":0,"version":"1.9.0"},{"date":"2024-04-04","total":1887,"delta":0,"version":"1.9.0"},{"date":"2024-04-05","total":1889,"delta":2,"version":"1.9.0"},{"date":"2024-04-06","total":1893,"delta":4,"version":"1.9.0"},{"date":"2024-04-07","total":1893,"delta":0,"version":"1.9.0"},{"date":"2024-04-08","total":1895,"delta":2,"version":"1.9.0"},{"date":"2024-04-09","total":1900,"delta":5,"version":"1.9.0"},{"date":"2024-04-10","total":1902,"delta":2,"version":"1.9.0"},{"date":"2024-04-11","total":1904,"delta":2,"version":"1.9.0"},{"date":"2024-04-12","total":1904,"delta":0,"version":"1.9.0"},{"date":"2024-04-13","total":1905,"delta":1,"version":"1.9.0"},{"date":"2024-04-14","total":1907,"delta":2,"version":"1.9.0"},{"date":"2024-04-15","total":1909,"delta":2,"version":"1.9.0"},{"date":"2024-04-16","total":1913,"delta":4,"version":"1.9.0"},{"date":"2024-04-03","total":2169,"delta":0,"version":"1.10.0"},{"date":"2024-04-04","total":2171,"delta":2,"version":"1.10.0"},{"date":"2024-04-05","total":2173,"delta":2,"version":"1.10.0"},{"date":"2024-04-06","total":2175,"delta":2,"version":"1.10.0"},{"date":"2024-04-07","total":2177,"delta":2,"version":"1.10.0"},{"date":"2024-04-08","total":2179,"delta":2,"version":"1.10.0"},{"date":"2024-04-09","total":2183,"delta":4,"version":"1.10.0"},{"date":"2024-04-10","total":2185,"delta":2,"version":"1.10.0"},{"date":"2024-04-11","total":2187,"delta":2,"version":"1.10.0"},{"date":"2024-04-12","total":2189,"delta":2,"version":"1.10.0"},{"date":"2024-04-13","total":2191,"delta":2,"version":"1.10.0"},{"date":"2024-04-14","total":2193,"delta":2,"version":"1.10.0"},{"date":"2024-04-15","total":2195,"delta":2,"version":"1.10.0"},{"date":"2024-04-16","total":2197,"delta":2,"version":"1.10.0"}]