[{"date":"2025-03-17","total":14044,"delta":5,"version":"131"},{"date":"2025-03-18","total":14047,"delta":3,"version":"131"},{"date":"2025-03-19","total":14049,"delta":2,"version":"131"},{"date":"2025-03-20","total":14051,"delta":2,"version":"131"},{"date":"2025-03-21","total":14052,"delta":1,"version":"131"},{"date":"2025-03-22","total":14054,"delta":2,"version":"131"},{"date":"2025-03-23","total":14064,"delta":10,"version":"131"},{"date":"2025-03-24","total":14066,"delta":2,"version":"131"},{"date":"2025-03-25","total":14068,"delta":2,"version":"131"},{"date":"2025-03-26","total":14081,"delta":13,"version":"131"},{"date":"2025-03-27","total":14083,"delta":2,"version":"131"},{"date":"2025-03-30","total":14101,"delta":18,"version":"131"},{"date":"2025-03-31","total":14103,"delta":2,"version":"131"},{"date":"2025-04-01","total":14105,"delta":2,"version":"131"}]